{
  "main": {
    "id": "f6df34c833e553f4",
    "type": "split",
    "children": [
      {
        "id": "d3f5eee89d818073",
        "type": "tabs",
        "children": [
          {
            "id": "48dfd29d50ed744b",
            "type": "leaf",
            "state": {
              "type": "markdown",
              "state": {
                "file": "Note/JAVA/Interface.md",
                "mode": "source",
                "source": false
              },
              "icon": "lucide-file",
              "title": "Interface"
            }
          }
        ]
      }
    ],
    "direction": "vertical"
  },
  "left": {
    "id": "5520e27a9b88c015",
    "type": "split",
    "children": [
      {
        "id": "47937cf8f9bd8ffd",
        "type": "tabs",
        "children": [
          {
            "id": "235e4a212391c32d",
            "type": "leaf",
            "state": {
              "type": "file-explorer",
              "state": {
                "sortOrder": "alphabetical",
                "autoReveal": false
              },
              "icon": "lucide-folder-closed",
              "title": "Files"
            }
          },
          {
            "id": "cb86361c0ef0bb2b",
            "type": "leaf",
            "state": {
              "type": "search",
              "state": {
                "query": "",
                "matchingCase": false,
                "explainSearch": false,
                "collapseAll": false,
                "extraContext": false,
                "sortOrder": "alphabetical"
              },
              "icon": "lucide-search",
              "title": "Search"
            }
          },
          {
            "id": "53cbb524ac62da44",
            "type": "leaf",
            "state": {
              "type": "bookmarks",
              "state": {},
              "icon": "lucide-bookmark",
              "title": "Bookmarks"
            }
          }
        ]
      }
    ],
    "direction": "horizontal",
    "width": 263.5
  },
  "right": {
    "id": "0b51c5841c246775",
    "type": "split",
    "children": [
      {
        "id": "84d39eedcf02deb1",
        "type": "tabs",
        "children": [
          {
            "id": "27ad823e56d23957",
            "type": "leaf",
            "state": {
              "type": "backlink",
              "state": {
                "file": "Note/Vpn.md",
                "collapseAll": false,
                "extraContext": false,
                "sortOrder": "alphabetical",
                "showSearch": false,
                "searchQuery": "",
                "backlinkCollapsed": false,
                "unlinkedCollapsed": true
              },
              "icon": "links-coming-in",
              "title": "Backlinks for Vpn"
            }
          },
          {
            "id": "f992a1872043d35a",
            "type": "leaf",
            "state": {
              "type": "outgoing-link",
              "state": {
                "file": "Note/Vpn.md",
                "linksCollapsed": false,
                "unlinkedCollapsed": true
              },
              "icon": "links-going-out",
              "title": "Outgoing links from Vpn"
            }
          },
          {
            "id": "3364bad8124a8e80",
            "type": "leaf",
            "state": {
              "type": "tag",
              "state": {
                "sortOrder": "frequency",
                "useHierarchy": true,
                "showSearch": false,
                "searchQuery": ""
              },
              "icon": "lucide-tags",
              "title": "Tags"
            }
          },
          {
            "id": "7715cd73ee1eb2e5",
            "type": "leaf",
            "state": {
              "type": "outline",
              "state": {
                "file": "Note/Vpn.md",
                "followCursor": false,
                "showSearch": false,
                "searchQuery": ""
              },
              "icon": "lucide-list",
              "title": "Outline of Vpn"
            }
          }
        ]
      }
    ],
    "direction": "horizontal",
    "width": 300,
    "collapsed": true
  },
  "left-ribbon": {
    "hiddenItems": {
      "switcher:Open quick switcher": false,
      "graph:Open graph view": false,
      "canvas:Create new canvas": false,
      "daily-notes:Open today's daily note": false,
      "templates:Insert template": false,
      "command-palette:Open command palette": false
    }
  },
  "active": "48dfd29d50ed744b",
  "lastOpenFiles": [
    "Note/JAVA/Charterers Streams Vs Bytes Streams.md",
    "Note/JAVA/Constructors.md",
    "Note/JAVA/Unit_2.md",
    "Note/JAVA/Data Types.md",
    "Note/JAVA/Collections in java.md",
    "Note/JAVA/building blocks of OOP.md",
    "Note/JAVA/EXCEPTIONS IN JAVA.md",
    "Note/JAVA/Unit 1.5.md",
    "Note/JAVA/UNIT 1.md",
    "Note/JAVA/List Interface.md",
    "Note/JAVA/Methods for threads.md",
    "Note/JAVA/Thread states.md",
    "Note/JAVA/Exception handling Keywords.md",
    "Note/JAVA/Final KeyWord.md",
    "Note/JAVA/Method Overriding.md",
    "Note/JAVA/Inheritance.md",
    "Note/JAVA/Interface.md",
    "Note/JAVA/Synchronization And Lock In Java.md",
    "Note/JAVA/Thread  Scheduling.md",
    "Note/JAVA/Implementation of Thread.md",
    "Note/JAVA/Threads.md",
    "Note/JAVA/FRATURES OF JAVA.md",
    "temp/TIME TABLE.md",
    "Note/JAVA/Implementation of runnable interface.md",
    "Note/JAVA/Untitled",
    "Note/JAVA/Variables.md",
    "[Note/JAVA/Thread states.md",
    "[Note/JAVA",
    "[Note",
    "malayalam",
    "temp",
    "Untitled.canvas"
  ]
}